CHANGELOG.txt
LICENSE.txt
MANIFEST.in
README.txt
__init__.py
helper_funcs.py
setup.py
multilabel_stratify.egg-info/PKG-INFO
multilabel_stratify.egg-info/SOURCES.txt
multilabel_stratify.egg-info/dependency_links.txt
multilabel_stratify.egg-info/requires.txt
multilabel_stratify.egg-info/top_level.txt