Metadata-Version: 1.1
Name: multilabel-stratify
Version: 0.0.2
Summary: A function that generates stratified test-train splits for multi-label data
Home-page: https://github.com/maxitron93/multilabel_stratify
Author: Maxi Merrillees
Author-email: maxi.merrillees@gmail.com
License: MIT
Keywords: multi-label multilabel stratify stratified split
Platform: UNKNOWN
Classifier: Development Status :: 5 - Production/Stable
Classifier: Intended Audience :: Education
Classifier: Operating System :: Microsoft :: Windows :: Windows 10
Classifier: License :: OSI Approved :: MIT License
Classifier: Programming Language :: Python :: 3
